INSTALL
LICENSE
MANIFEST.in
README.rst
setup.py
docs/examples/local_settings.py.example
packaging/VERSION
packaging/requirements-test.txt
packaging/requirements.txt
prngmgr/__init__.py
prngmgr/admin.py
prngmgr/apps.py
prngmgr/classy_views.py
prngmgr/forms.py
prngmgr/models.py
prngmgr/settings.py
prngmgr/snmp.py
prngmgr/tests.py
prngmgr/urls.py
prngmgr.egg-info/PKG-INFO
prngmgr.egg-info/SOURCES.txt
prngmgr.egg-info/dependency_links.txt
prngmgr.egg-info/requires.txt
prngmgr.egg-info/top_level.txt
prngmgr/api/__init__.py
prngmgr/api/datatables.py
prngmgr/api/serializers.py
prngmgr/api/urls.py
prngmgr/api/views.py
prngmgr/management/__init__.py
prngmgr/management/commands/__init__.py
prngmgr/management/commands/prngmgr-sync-sessions.py
prngmgr/management/commands/prngmgr-sync.py
prngmgr/management/commands/prngmgr-whoami.py
prngmgr/migrations/0001_initial.py
prngmgr/migrations/0002_auto_20161005_0958.py
prngmgr/migrations/0003_remove_peeringsession_general_state.py
prngmgr/migrations/0004_peeringsession_accepted_prefixes.py
prngmgr/migrations/0005_auto_20161008_1250.py
prngmgr/migrations/0006_auto_20161008_1336.py
prngmgr/migrations/0007_auto_20161008_1643.py
prngmgr/migrations/0008_auto_20161010_1656.py
prngmgr/migrations/__init__.py
prngmgr/policy/__init__.py
prngmgr/policy/autnums.py
prngmgr/policy/communities.py
prngmgr/policy/prefixes.py
prngmgr/static/css/base.css
prngmgr/static/css/login.css
prngmgr/static/img/favicon.ico
prngmgr/static/img/logo.jpg
prngmgr/static/img/logo_sqr.jpg
prngmgr/static/js/index.js
prngmgr/templates/prngmgr/ajax_table.html
prngmgr/templates/prngmgr/base.html
prngmgr/templates/prngmgr/css.html
prngmgr/templates/prngmgr/footer.html
prngmgr/templates/prngmgr/form.html
prngmgr/templates/prngmgr/index.html
prngmgr/templates/prngmgr/js.html
prngmgr/templates/prngmgr/login.html
prngmgr/templates/prngmgr/navbar.html
prngmgr/templates/prngmgr/table.html
prngmgr/views/__init__.py
prngmgr/views/interfaces.py
prngmgr/views/routers.py
prngmgr/views/utils.py
test/__init__.py
test/exec.py
test/settings.py